redoubt_agent/__init__.py
redoubt_agent/redoubt_sdk.py
redoubt_agent-0.2.0.dist-info/LICENSE
redoubt_agent-0.2.0.dist-info/METADATA
redoubt_agent-0.2.0.dist-info/WHEEL
redoubt_agent-0.2.0.dist-info/top_level.txt
redoubt_agent-0.2.0.dist-info/RECORD
