Metadata-Version: 2.1
Name: redoubt-agent
Version: 0.2.0
Summary: re:doubt Bot Python SDK
Home-page: https://www.redoubt.online/
Author: maksymds
Author-email: redoubt@devnull.ae
License: Apache 2.0
Project-URL: Github, https://github.com/re-doubt/redoubt-bot-python-sdk
Project-URL: Documentation, https://docs.redoubt.online/
Keywords: TON,redoubt,sdk
Classifier: Development Status :: 4 - Beta
Classifier: Intended Audience :: Developers
Classifier: License :: OSI Approved :: Apache Software License
Classifier: Operating System :: OS Independent
Classifier: Programming Language :: Python :: 3
Classifier: Programming Language :: Python :: 3.8
Classifier: Programming Language :: Python :: 3.9
Classifier: Programming Language :: Python :: 3.10
Classifier: Programming Language :: Python :: 3.11
Classifier: Topic :: Software Development :: Libraries :: Python Modules
Requires-Python: >=3.8
License-File: LICENSE
Requires-Dist: gql (==3.4.1)
Requires-Dist: loguru (==0.7.0)
Requires-Dist: aiohttp (==3.8.4)
Requires-Dist: requests-toolbelt (==1.0.0)
Requires-Dist: websockets (==11.0.3)
